[
  {
    "name": {
      "simple": "directory",
      "qualified": "masd.generation.cpp.directory"
    },
    "archetype_location": {
      "kernel": "masd",
      "backend": "masd.generation.cpp"
    },
    "value_type": "text",
    "template_kind": "instance",
    "scope": "root_module",
    "default_value": "cpp"
  },
  {
    "name": {
      "simple": "supported"
    },
    "archetype_location": {
      "kernel": "masd",
      "backend": "masd.generation.cpp"
    },
    "value_type": "boolean",
    "template_kind": "facet_template",
    "scope": "entity",
    "default_value": true
  },
  {
    "name": {
      "simple": "overwrite"
    },
    "archetype_location": {
      "kernel": "masd",
      "backend": "masd.generation.cpp"
    },
    "value_type": "boolean",
    "template_kind": "facet_template",
    "scope": "any",
    "default_value": true
  },
  {
    "name": {
      "simple": "overwrite"
    },
    "archetype_location": {
      "kernel": "masd",
      "backend": "masd.generation.cpp"
    },
    "value_type": "boolean",
    "template_kind": "archetype_template",
    "scope": "any"
  },
  {
    "name": {
      "simple": "profile",
      "qualified": "masd.generation.cpp.profile"
    },
    "archetype_location": {
      "kernel": "masd",
      "backend": "masd.generation.cpp"
    },
    "value_type": "text",
    "template_kind": "instance",
    "scope": "entity",
    "default_value": "default"
  },
  {
    "name": {
      "simple": "inclusion_required",
      "qualified": "masd.generation.cpp.inclusion_required"
    },
    "archetype_location": {
      "kernel": "masd",
      "backend": "masd.generation.cpp"
    },
    "value_type": "boolean",
    "template_kind": "instance",
    "scope": "entity",
    "default_value": true
  },
  {
    "name": {
      "simple": "primary_inclusion_directive",
      "formatter_group": "masd.generation.cpp.header_files"
    },
    "archetype_location": {
      "kernel": "masd",
      "backend": "masd.generation.cpp"
    },
    "value_type": "text",
    "template_kind": "archetype_template",
    "scope": "entity"
  },
  {
    "name": {
      "simple": "secondary_inclusion_directive",
      "formatter_group": "masd.generation.cpp.header_files"
    },
    "archetype_location": {
      "kernel": "masd",
      "backend": "masd.generation.cpp"
    },
    "value_type": "text_collection",
    "template_kind": "archetype_template",
    "scope": "entity"
  },
  {
    "name": {
      "simple": "source_directory_name",
      "qualified": "masd.generation.cpp.source_directory_name"
    },
    "archetype_location": {
      "kernel": "masd",
      "backend": "masd.generation.cpp"
    },
    "value_type": "text",
    "template_kind": "instance",
    "scope": "root_module",
    "default_value": "src"
  },
  {
    "name": {
      "simple": "include_directory_name",
      "qualified": "masd.generation.cpp.include_directory_name"
    },
    "archetype_location": {
      "kernel": "masd",
      "backend": "masd.generation.cpp"
    },
    "value_type": "text",
    "template_kind": "instance",
    "scope": "root_module",
    "default_value": "include"
  },
  {
    "name": {
      "simple": "tests_directory_name",
      "qualified": "masd.generation.cpp.tests_directory_name"
    },
    "archetype_location": {
      "kernel": "masd",
      "backend": "masd.generation.cpp"
    },
    "value_type": "text",
    "template_kind": "instance",
    "scope": "root_module",
    "default_value": "tests"
  },
  {
    "name": {
      "simple": "header_file_extension",
      "qualified": "masd.generation.cpp.header_file_extension"
    },
    "archetype_location": {
      "kernel": "masd",
      "backend": "masd.generation.cpp"
    },
    "value_type": "text",
    "template_kind": "instance",
    "scope": "root_module",
    "default_value": "hpp"
  },
  {
    "name": {
      "simple": "implementation_file_extension",
      "qualified": "masd.generation.cpp.implementation_file_extension"
    },
    "archetype_location": {
      "kernel": "masd",
      "backend": "masd.generation.cpp"
    },
    "value_type": "text",
    "template_kind": "instance",
    "scope": "root_module",
    "default_value": "cpp"
  },
  {
    "name": {
      "simple": "enable_unique_file_names",
      "qualified": "masd.generation.cpp.enable_unique_file_names"
    },
    "archetype_location": {
      "kernel": "masd",
      "backend": "masd.generation.cpp"
    },
    "value_type": "boolean",
    "template_kind": "instance",
    "scope": "root_module",
    "default_value": true
  },
  {
    "name": {
      "simple": "requires_manual_default_constructor",
      "qualified": "masd.generation.cpp.aspect.requires_manual_default_constructor"
    },
    "archetype_location": {
      "kernel": "masd",
      "backend": "masd.generation.cpp"
    },
    "value_type": "boolean",
    "template_kind": "instance",
    "scope": "entity",
    "default_value": false
  },
  {
    "name": {
      "simple": "requires_manual_move_constructor",
      "qualified": "masd.generation.cpp.aspect.requires_manual_move_constructor"
    },
    "archetype_location": {
      "kernel": "masd",
      "backend": "masd.generation.cpp"
    },
    "value_type": "boolean",
    "template_kind": "instance",
    "scope": "entity",
    "default_value": false
  },
  {
    "name": {
      "simple": "requires_stream_manipulators",
      "qualified": "masd.generation.cpp.aspect.requires_stream_manipulators"
    },
    "archetype_location": {
      "kernel": "masd",
      "backend": "masd.generation.cpp"
    },
    "value_type": "boolean",
    "template_kind": "instance",
    "scope": "entity",
    "default_value": false
  },
  {
    "name": {
      "simple": "disable_facet_directories",
      "qualified": "masd.generation.cpp.disable_facet_directories"
    },
    "archetype_location": {
      "kernel": "masd",
      "backend": "masd.generation.cpp"
    },
    "value_type": "boolean",
    "template_kind": "instance",
    "scope": "root_module",
    "default_value": false
  },
  {
    "name": {
      "simple": "standard",
      "qualified": "masd.generation.cpp.standard"
    },
    "archetype_location": {
      "kernel": "masd",
      "backend": "masd.generation.cpp"
    },
    "value_type": "text",
    "template_kind": "instance",
    "scope": "root_module",
    "default_value": "c++-14"
  },
  {
    "name": {
      "simple": "kernel",
      "qualified": "masd.generation.cpp.helper.family"
    },
    "archetype_location": {
      "kernel": "masd",
      "backend": "masd.generation.cpp"
    },
    "value_type": "text",
    "template_kind": "instance",
    "scope": "entity",
    "default_value": "Default"
  },
  {
    "name": {
      "simple": "string_conversion_method",
      "qualified": "masd.generation.cpp.streaming.string_conversion_method"
    },
    "archetype_location": {
      "kernel": "masd",
      "backend": "masd.generation.cpp"
    },
    "value_type": "text",
    "template_kind": "instance",
    "scope": "entity",
    "default_value": ""
  },
  {
    "name": {
      "simple": "requires_quoting",
      "qualified": "masd.generation.cpp.streaming.requires_quoting"
    },
    "archetype_location": {
      "kernel": "masd",
      "backend": "masd.generation.cpp"
    },
    "value_type": "boolean",
    "template_kind": "instance",
    "scope": "entity",
    "default_value": false
  },
  {
    "name": {
      "simple": "remove_unprintable_characters",
      "qualified": "masd.generation.cpp.streaming.remove_unprintable_characters"
    },
    "archetype_location": {
      "kernel": "masd",
      "backend": "masd.generation.cpp"
    },
    "value_type": "boolean",
    "template_kind": "instance",
    "scope": "entity",
    "default_value": false
  },
  {
    "name": {
      "simple": "postfix",
      "qualified": "masd.generation.cpp.cmake.source_cmakelists.postfix"
    },
    "archetype_location": {
      "kernel": "masd",
      "backend": "masd.generation.cpp",
      "facet": "masd.generation.cpp.cmake",
      "archetype": "masd.generation.cpp.cmake.source_cmakelists.postfix"
    },
    "value_type": "text",
    "template_kind": "instance",
    "scope": "root_module",
    "default_value": ""
  },
  {
    "name": {
      "simple": "postfix",
      "qualified": "masd.generation.cpp.cmake.include_cmakelists.postfix"
    },
    "archetype_location": {
      "kernel": "masd",
      "backend": "masd.generation.cpp",
      "facet": "masd.generation.cpp.cmake",
      "archetype": "masd.generation.cpp.cmake.include_cmakelists.postfix"
    },
    "value_type": "text",
    "template_kind": "instance",
    "scope": "root_module",
    "default_value": ""
  },
  {
    "name": {
      "simple": "postfix",
      "qualified": "masd.generation.cpp.msbuild.targets.postfix"
    },
    "archetype_location": {
      "kernel": "masd",
      "backend": "masd.generation.cpp",
      "facet": "masd.generation.cpp.cmake",
      "archetype": "masd.generation.cpp.msbuild.targets.postfix"
    },
    "value_type": "text",
    "template_kind": "instance",
    "scope": "root_module",
    "default_value": ""
  },
  {
    "name": {
      "simple": "project_solution_guid",
      "qualified": "masd.generation.cpp.visual_studio.project_solution_guid"
    },
    "archetype_location": {
      "kernel": "masd",
      "backend": "masd.generation.cpp",
      "facet": "masd.generation.cpp.visual_studio"
    },
    "value_type": "text",
    "template_kind": "instance",
    "scope": "root_module",
    "default_value": "00000000-0000-0000-0000-000000000000"
  },
  {
    "name": {
      "simple": "project_guid",
      "qualified": "masd.generation.cpp.visual_studio.project_guid"
    },
    "archetype_location": {
      "kernel": "masd",
      "backend": "masd.generation.cpp",
      "facet": "masd.generation.cpp.visual_studio"
    },
    "value_type": "text",
    "template_kind": "instance",
    "scope": "root_module",
    "default_value": "00000000-0000-0000-0000-000000000000"
  },
  {
    "name": {
      "simple": "postfix",
      "qualified": "masd.generation.cpp.visual_studio.solution.postfix"
    },
    "archetype_location": {
      "kernel": "masd",
      "backend": "masd.generation.cpp",
      "facet": "masd.generation.cpp.visual_studio",
      "archetype": "masd.generation.cpp.visual_studio.solution.postfix"
    },
    "value_type": "text",
    "template_kind": "instance",
    "scope": "root_module",
    "default_value": ""
  },
  {
    "name": {
      "simple": "postfix",
      "qualified": "masd.generation.cpp.visual_studio.project.postfix"
    },
    "archetype_location": {
      "kernel": "masd",
      "backend": "masd.generation.cpp",
      "facet": "masd.generation.cpp.visual_studio",
      "archetype": "masd.generation.cpp.visual_studio.project.postfix"
    },
    "value_type": "text",
    "template_kind": "instance",
    "scope": "root_module",
    "default_value": ""
  }
]
